<?xml version='1.0' encoding='UTF-8'?>
<search_results><query id="7083">I'm on the road again</query><engine status="OK" timestamp="2014-04-20 21:03:36" name="Reddit" id="FW14-e153"/><snippets><snippet id="FW14-e153-7083-01"><link cache="FW14-topics-docs/e153/7083_01.html" timestamp="2014-04-20 21:03:37">http://www.reddit.com/r/pettyrevenge/comments/14lue6/dicks_dont_deserve_my_parking_spot/</link><title>Dicks don't deserve my parking spot</title></snippet><snippet id="FW14-e153-7083-02"><link cache="FW14-topics-docs/e153/7083_02.html" timestamp="2014-04-20 21:04:49">http://www.reddit.com/r/AskReddit/comments/11rkln/update_leaving_my_abusive_boyfriend_tomorrow_did/</link><title>UPDATE: Leaving my abusive boyfriend tomorrow. Did I do ok?</title></snippet><snippet id="FW14-e153-7083-03"><link cache="FW14-topics-docs/e153/7083_03.html" timestamp="2014-04-20 21:05:18">http://www.reddit.com/r/IAmA/comments/1s6mi5/im_trent_reznor_of_nine_inch_nails_ask_me_anything/</link><title>I'm Trent Reznor of Nine Inch Nails. Ask me anything.</title></snippet><snippet id="FW14-e153-7083-04"><link cache="FW14-topics-docs/e153/7083_04.html" timestamp="2014-04-20 21:08:15">http://www.reddit.com/r/asoiaf/comments/1nlez7/spoilers_all_question_about_the_state_of/</link><title>(Spoilers All) Question about the state of technology in Westeros/Essos</title></snippet><snippet id="FW14-e153-7083-05"><link cache="FW14-topics-docs/e153/7083_05.html" timestamp="2014-04-20 21:10:43">http://www.reddit.com/r/Diablo/comments/yfsaw/i_did_that_amaa_a_few_weeks_back_it_was_great_so/</link><title>I did that AMAA a few weeks back. It was great, so I'm doing a giveaway to say thanks!</title></snippet><snippet id="FW14-e153-7083-06"><link cache="FW14-topics-docs/e153/7083_06.html" timestamp="2014-04-20 21:11:39">http://www.reddit.com/r/opiates/comments/1rgm1k/i_think_i_caught_the_dumb_im_paying_for_my_slip/</link><title>I think I caught the dumb. I'm paying for my slip up bog time. :/</title></snippet><snippet id="FW14-e153-7083-07"><link cache="FW14-topics-docs/e153/7083_07.html" timestamp="2014-04-20 21:15:03">http://www.reddit.com/r/books/comments/13s2ao/looking_for_a_stories_where_everything_is_shit/</link><title>Looking for a stories where everything is shit then everything gets better and it seems like everything is going to be fine but everything goes back to being shitty again. Everybody's sad,dead or desperate it sucks and the story ends.</title></snippet><snippet id="FW14-e153-7083-08"><link cache="FW14-topics-docs/e153/7083_08.html" timestamp="2014-04-20 21:18:06">http://www.reddit.com/r/AskReddit/comments/cn67i/i_got_rearended_today_the_guy_said_it_was_my/</link><title>I got rear-ended today. The guy said it was my fault. Could someone walk me through this?</title></snippet><snippet id="FW14-e153-7083-09"><link cache="FW14-topics-docs/e153/7083_09.html" timestamp="2014-04-20 21:22:30">http://www.reddit.com/r/Velo/comments/1a9kod/recently_hit_by_a_car_while_riding_ive_barely/</link><title>Recently hit by a car while riding. I've barely touched my road bike since. Not sure how to deal with it.</title></snippet><snippet id="FW14-e153-7083-10"><link cache="FW14-topics-docs/e153/7083_10.html" timestamp="2014-04-20 21:26:01">http://www.reddit.com/r/Games/comments/zifo3/world_of_warcraft_and_its_massive_growing_pile_of/</link><title>World of Warcraft and it's massive growing pile of unused content.</title></snippet></snippets></search_results>