<?xml version='1.0' encoding='UTF-8'?>
<search_results><query id="7008">jesse van ruller solo transcriptions</query><engine status="OK" timestamp="2014-04-20 00:30:03" name="Amazon" id="FW14-e140"/><snippets><snippet id="FW14-e140-7008-01"><link cache="FW14-topics-docs/e140/7008_01.html" timestamp="2014-04-20 00:30:05">http://www.amazon.com/Solo-The-Story-African-Wild/dp/0395183219/ref=sr_1_fkmr0_1/189-9752438-3693711?ie=UTF8&amp;qid=1397946604&amp;sr=8-1-fkmr0&amp;keywords=jesse+van+ruller+solo+transcriptions</link><title>Solo: The Story of an African Wild Dog by Hugo van Lawick (1974)</title><thumb cache="FW14-topics-docs/e140/7008_01_thumb.jpg">http://ecx.images-amazon.com/images/I/51XpZGAEzUL._AA160_.jpg</thumb></snippet><snippet id="FW14-e140-7008-02"><link cache="FW14-topics-docs/e140/7008_02.html" timestamp="2014-04-20 00:33:15">http://www.amazon.com/Fame-Eddie-Barth/dp/B00008WJBF/ref=sr_1_fkmr0_2/189-9752438-3693711?ie=UTF8&amp;qid=1397946604&amp;sr=8-2-fkmr0&amp;keywords=jesse+van+ruller+solo+transcriptions</link><title>Fame (2004) Starring Eddie Barth, Irene Cara, Lee Curreri and Laura Dean</title><thumb cache="FW14-topics-docs/e140/7008_02_thumb.jpg">http://ecx.images-amazon.com/images/I/41ju-KLxW7L._AA160_.jpg</thumb></snippet><snippet id="FW14-e140-7008-03"><link cache="FW14-topics-docs/e140/7008_03.html" timestamp="2014-04-20 00:36:58">http://www.amazon.com/myLife-Purple-Protective-Generation-Rubberized/dp/B00J2A4758/ref=sr_1_fkmr0_3/189-9752438-3693711?ie=UTF8&amp;qid=1397946604&amp;sr=8-3-fkmr0&amp;keywords=jesse+van+ruller+solo+transcriptions</link><title>myLife (TM) Purple - Colorful Bubbles Series (3 Piece Protective) Hard and Soft Case for the iPhone 4/4S (4G)... by myLife Brand Products</title><thumb cache="FW14-topics-docs/e140/7008_03_thumb.jpg">http://ecx.images-amazon.com/images/I/51KVQD4WMzL._AA160_.jpg</thumb></snippet><snippet id="FW14-e140-7008-04"><link cache="FW14-topics-docs/e140/7008_04.html" timestamp="2014-04-20 00:38:05">http://www.amazon.com/Circles-Jesse-Van-Ruller/dp/B00008V5UY/ref=sr_1_fkmr1_1/189-9752438-3693711?ie=UTF8&amp;qid=1397946604&amp;sr=8-1-fkmr1&amp;keywords=jesse+van+ruller+solo+transcriptions</link><title>Circles by Jesse Van Ruller (May 27, 2003)</title><thumb cache="FW14-topics-docs/e140/7008_04_thumb.jpg">http://ecx.images-amazon.com/images/I/51l7bQbTO8L._AA160_.jpg</thumb></snippet><snippet id="FW14-e140-7008-05"><link cache="FW14-topics-docs/e140/7008_05.html" timestamp="2014-04-20 00:40:58">http://www.amazon.com/Here-There-Jesse-Van-Ruller/dp/B0000636AW/ref=sr_1_fkmr1_2/189-9752438-3693711?ie=UTF8&amp;qid=1397946604&amp;sr=8-2-fkmr1&amp;keywords=jesse+van+ruller+solo+transcriptions</link><title>Here and There by Jesse Van Ruller (Mar 12, 2002)</title><thumb cache="FW14-topics-docs/e140/7008_05_thumb.jpg">http://ecx.images-amazon.com/images/I/51hYxI-NF3L._AA160_.jpg</thumb></snippet><snippet id="FW14-e140-7008-06"><link cache="FW14-topics-docs/e140/7008_06.html" timestamp="2014-04-20 00:43:56">http://www.amazon.com/Live-Murphys-Law-Jesse-Ruller/dp/B0002VL76I/ref=sr_1_fkmr1_3/189-9752438-3693711?ie=UTF8&amp;qid=1397946604&amp;sr=8-3-fkmr1&amp;keywords=jesse+van+ruller+solo+transcriptions</link><title>Live at Murphy's Law by Jesse Van Ruller (2004) - Import</title><thumb cache="FW14-topics-docs/e140/7008_06_thumb.jpg">http://ecx.images-amazon.com/images/I/51K1ARClyXL._AA160_.jpg</thumb></snippet></snippets></search_results>