<?xml version='1.0' encoding='UTF-8'?>
<search_results><query id="7405">light therapy</query><engine status="OK" timestamp="2014-04-22 22:20:29" name="Foursquare" id="FW14-e095"/><snippets><snippet id="FW14-e095-7405-01"><link cache="FW14-topics-docs/e095/7405_01.html" timestamp="2014-04-22 22:20:30">https://foursquare.com/v/light-therapy/50a2d078e4b0d13716c8e6b2</link><title>Light Therapy</title><description>* 1.

Light Therapy

?

Non-Profit •</description></snippet><snippet id="FW14-e095-7405-02"><link cache="FW14-topics-docs/e095/7405_02.html" timestamp="2014-04-22 22:22:21">https://foursquare.com/v/the-g-spa-international/4e7b797f814d5f754861c326</link><title>The G Spa International</title><description>* 2.

The G Spa International

?

9001 Woodyard Rd Ste D

Spa • View Menu •

On the menu: , this disorder was treated using ultraviolet light therapy (UVB); however, this method does not allow the doctor to safely treat specific, sometimes small areas

Save</description><thumb cache="FW14-topics-docs/e095/7405_02_thumb.png">https://ss1.4sqi.net/img/icon-menu-f1674d6544f5111a62cc947f18bbcbde.png</thumb></snippet><snippet id="FW14-e095-7405-03"><link cache="FW14-topics-docs/e095/7405_03.html" timestamp="2014-04-22 22:24:35">https://foursquare.com/v/radiance-medspa-washington-dc/4c5458d8a724e21ee39d3ff6</link><title>Radiance MedSpa</title><description>* 3.

Radiance MedSpa

?

3105 14th St NW

Spa • View Menu •

On the menu: / light energy. Ipl/laser therapy also stimulates collagen production, resulting in plumper skin, improvement in the appearance of fine lines, &amp; smaller pores. The end result is smoother, healthier &amp; younger appearing skin.

Save</description><thumb cache="FW14-topics-docs/e095/7405_03_thumb.png">https://ss1.4sqi.net/img/icon-menu-f1674d6544f5111a62cc947f18bbcbde.png</thumb></snippet><snippet id="FW14-e095-7405-04"><link cache="FW14-topics-docs/e095/7405_04.html" timestamp="2014-04-22 22:26:01">https://foursquare.com/v/blu-water-day-spa-kensington-md/4bb35ec8eb3e95215603cb0a</link><title>Blu Water Day Spa</title><description>* 4.

Blu Water Day Spa

?

5234 Nicholson Ln

Spa • View Menu •

On the menu: LED Light Treatment: LED light therapy is an FDA-approved cosmetic procedure that is gentle, painless, safe &amp; effective. unique photopulsation technology uses light emitting diodes (LED’s) to diminish fine lines, wrinkles &amp; age spots while tightening pores, plumping &amp; smoothing the skin. the LED therapy is safe for all skin types &amp; also extremely effective w/ difficult acne cases where an ongoing acne treatment appears to have stalled.

Save</description><thumb cache="FW14-topics-docs/e095/7405_04_thumb.png">https://ss1.4sqi.net/img/icon-menu-f1674d6544f5111a62cc947f18bbcbde.png</thumb></snippet></snippets></search_results>