<?xml version='1.0' encoding='UTF-8'?>
<search_results><query id="7121">who is the man in the m&amp;m commercial</query><engine status="OK" timestamp="2014-04-21 19:01:49" name="Ask" id="FW14-e052"/><snippets><snippet id="FW14-e052-7121-01"><link cache="FW14-topics-docs/e052/7121_01.html" timestamp="2014-04-21 19:01:50">http://www.youtube.com/watch?v=jg-0Mq7I9b0</link><title>William Levy - M&amp;M's Commercial \- YouTube</title><description>Jul 30, 2012 ... William Levy - M&amp;M's Commercial ... M&amp;Ms Commercial Collection by josiah o' keefe 27,958 views · 1:01 .... Daaang! He is one handsome man.</description></snippet><snippet id="FW14-e052-7121-02"><link cache="FW14-topics-docs/e052/7121_02.html" timestamp="2014-04-21 19:04:03">http://www.youtube.com/watch?v=6QMb16bxJvY</link><title>M&amp;M's 'One Track Mind' Commercial featuring William Levy ...</title><description>Jul 29, 2012 ... M&amp;M's 'One Track Mind' Commercial featuring William Levy @WillyLevy29 &amp; Ms. .... Can u imagine that man talking to u like that over lunch?</description></snippet><snippet id="FW14-e052-7121-03"><link cache="FW14-topics-docs/e052/7121_03.html" timestamp="2014-04-21 19:06:33">http://www.youtube.com/watch?v=YFk0Q3zS3PE</link><title>William Levy - M&amp;M's commercial in Spanish | Greek subs - YouTube</title><description>Jul 31, 2012 ... http://www.facebook.com/GreciaTeEsperaWilliamLevy JOIN US and FIND everything about William Levy. • Info, News, Videos, Photos •</description></snippet><snippet id="FW14-e052-7121-04"><link cache="FW14-topics-docs/e052/7121_04.html" timestamp="2014-04-21 19:07:12">http://www.youtube.com/watch?v=17jwY1RSimk</link><title>William Levy at M&amp;M's Commercial \- YouTube</title><description>Jul 31, 2012 ... William Levy at M&amp;M's Commercial \- YouTube. Subscribe 2,149. All comments ( 44). Share your thoughts. Top comments. Stream. Rex Firefly.</description></snippet><snippet id="FW14-e052-7121-05"><link cache="FW14-topics-docs/e052/7121_05.html" timestamp="2014-04-21 19:10:12">http://www.juanofwords.com/2012/08/william-levy-he-can-make-even-an-mms-commercial-sizzle/</link><title>William Levy: He Can Make Even an M&amp;M's Commercial Sizzle ...</title><description>Aug 22, 2012 ... Unless you're living under a piedra somewhere chances are you've already seen this hugely popular 30 second commercial either online or on ...</description></snippet><snippet id="FW14-e052-7121-06"><link cache="FW14-topics-docs/e052/7121_06.html" timestamp="2014-04-21 19:13:35">http://whoisthatguyinthecommercial.tumblr.com/post/33577508868/william-levy-and-m-m-ms-brown-in-one-track-mind</link><title>Who Is That Guy In The Commercial? - William Levy and M&amp;M Ms ...</title><description>William Levy and M&amp;M Ms. Brown in One Track Mind. Advertising ... William Levy. William was declared 2012's Sexiest Man Alive by People En Espanol. image.</description></snippet><snippet id="FW14-e052-7121-07"><link cache="FW14-topics-docs/e052/7121_07.html" timestamp="2014-04-21 19:14:21">http://www.huffingtonpost.com/2014/02/02/mm-super-bowl-commercial-2014-yellow_n_4708911.html</link><title>M&amp;M Super Bowl Commercial 2014 Features Yellow M&amp;M Being ...</title><description>Feb 2, 2014 ... M&amp;M Super Bowl Commercial 2014 Features Yellow M&amp;M Being ... chocolate-y treat was taken to a mysterious mansion, where a man ...</description></snippet><snippet id="FW14-e052-7121-08"><link cache="FW14-topics-docs/e052/7121_08.html" timestamp="2014-04-21 19:17:22">http://www.superbowl-commercials.org/33108.html</link><title>M&amp;M's Delivers a Fine Super Bowl Spot | 2014 Super Bowl ...</title><description>Feb 2, 2014 ... In the cinematic M&amp;M's spot, which starts off in the vein of a classic ... It's a funny enough commercial, and certainly well-produced, but it's not ...</description></snippet><snippet id="FW14-e052-7121-09"><link cache="FW14-topics-docs/e052/7121_09.html" timestamp="2014-04-21 19:18:06">http://www.justjared.com/2014/02/02/mms-super-bowl-commercial-2014-russian-mob/</link><title>M&amp;Ms Super Bowl Commercial 2014 – Russian Mob ... \- Just Jared</title><description>Feb 2, 2014 ... Check out this yellow peanut M&amp;M about to become dessert in the 2014 Super Bowl ... Be sure to watch the commercial below, and stay tuned to .... 'Mad Men' Review: All In 'A Day's Work' For Don; Lindsay Lohan's Words For ...</description></snippet><snippet id="FW14-e052-7121-10"><link cache="FW14-topics-docs/e052/7121_10.html" timestamp="2014-04-21 19:20:29">http://uproxx.com/tv/2014/01/50-questions-disturbing-hell-commercial-lady-devours-talking-mm-car/</link><title>50 Questions About That One Disturbing As Hell M&amp;M Commercial</title><description>Jan 6, 2014 ... Here are 50 questions about that disturbing M&amp;M commercial where the ... You failed to mention that in the second commercial, there are men ...</description></snippet></snippets></search_results>