<?xml version='1.0' encoding='UTF-8'?>
<search_results><query id="7261">elvish language</query><engine status="OK" timestamp="2014-04-23 03:43:13" name="Ask" id="FW14-e052"/><snippets><snippet id="FW14-e052-7261-01"><link cache="FW14-topics-docs/e052/7261_01.html" timestamp="2014-04-23 03:43:14">http://www.starchamber.com/paracelsus/elvish/elvish-in-ten-minutes.html</link><title>Write Your Name in Elvish in Ten Minutes</title><description>You want to write your name in Elvish, but every place you go seems to make it harder than it ought to be. Elvish writing looks beautiful and mysterious, but does  ...</description></snippet><snippet id="FW14-e052-7261-02"><link cache="FW14-topics-docs/e052/7261_02.html" timestamp="2014-04-23 03:44:12">http://www.omniglot.com/writing/tengwar.htm</link><title>Tengwar (Elvish) alphabet - Omniglot</title><description>Information about Tengwar script, which appears in the Lord of the Rings and other books by J.R.R. Tolkien and can be used to write Elvish languages such as  ...</description></snippet><snippet id="FW14-e052-7261-03"><link cache="FW14-topics-docs/e052/7261_03.html" timestamp="2014-04-23 03:45:40">http://www.grey-company.org/Circle/language/phrase.htm</link><title>Elven Phrases</title><description>Elven Phrases The Phrase Guide of Tel'Quessir is being ...</description></snippet><snippet id="FW14-e052-7261-04"><link cache="FW14-topics-docs/e052/7261_04.html" timestamp="2014-04-23 03:46:38">http://lotr.wikia.com/wiki/Elvish_languages</link><title>Elvish languages \- Lord of the Rings Wiki</title><description>There are several different Elvish languages of which Quenya and Sindarin are the most common and well known, but there were many variations and dialects.</description></snippet><snippet id="FW14-e052-7261-05"><link cache="FW14-topics-docs/e052/7261_05.html" timestamp="2014-04-23 03:47:22">http://www.elvish.org/</link><title>The Elvish Linguistic Fellowship</title><description>Sep 22, 2013 ... The Elvish Linguistic Fellowship (E.L.F.) is an international, not-for-profit organization devoted to the scholarly study of the invented languages ...</description></snippet><snippet id="FW14-e052-7261-06"><link cache="FW14-topics-docs/e052/7261_06.html" timestamp="2014-04-23 03:48:42">http://tolkiengateway.net/wiki/Elvish</link><title>Elvish \- Tolkien Gateway</title><description>After Tolkien's time, others have invented Elvish languages in their own fiction. Some of them borrow elements from ...</description></snippet><snippet id="FW14-e052-7261-07"><link cache="FW14-topics-docs/e052/7261_07.html" timestamp="2014-04-23 03:50:13">http://www.arwen-undomiel.com/elvish.html</link><title>Elvish \- Arwen-Undomiel.com</title><description>An Introduction to Elvish Read a brief history of Elvish, terms of use, and credits. Useful Links A list of ... A list of English names translated into Elvish languages.</description></snippet><snippet id="FW14-e052-7261-08"><link cache="FW14-topics-docs/e052/7261_08.html" timestamp="2014-04-23 03:51:24">http://www.arwen-undomiel.com/elvish/phrases.html</link><title>Elvish :: Useful Phrases :: - Arwen-Undomiel.com</title><description>Elvish Line Phonetic Transcription /fə.ˈnɛ.tɪk ˌʧɹæn.ˈskɹɪp.ʃən/. Phrases are taken (with the premission of their writer) from Merin Essi ar Quenteli!</description></snippet></snippets></search_results>