<?xml version='1.0' encoding='UTF-8'?>
<search_results><query id="7173"> severed spinal cord</query><engine status="OK" timestamp="2014-04-21 23:50:38" name="Pronto" id="FW14-e146"/><snippets><snippet id="FW14-e146-7173-01"><link cache="FW14-topics-docs/e146/7173_01.html" timestamp="2014-04-21 23:50:39">http://www.pronto.com/prodRedirExitInterst.do?exitPoint=nraq&amp;merchantProductId=1589551563&amp;pageLocation=ProductImage&amp;parentId=-290ae334-145861e246f-1d0d&amp;shouldLookupGuidesterCpc=true</link><title>Sekitsui Sekizui Janaru = Spine and Spinal Cord</title><description>Sekitsui Sekizui Janaru = Spine and Spinal Cord</description><thumb cache="FW14-topics-docs/e146/7173_01_thumb.jpg">http://cache-images.pronto.com/thumb2.php?src=http%3A%2F%2Fimages.pronto.com%2Fimages%2Fproduction%2Fproducts%2F61%2Fa8%2Fimag9a52bf1e7be258b45578431b08e3-1378873158_119x160.jpg&amp;wmax=180&amp;hmax=180&amp;quality=80&amp;bgcol=FFFFFF</thumb></snippet><snippet id="FW14-e146-7173-02"><link cache="FW14-topics-docs/e146/7173_02.html" timestamp="2014-04-21 23:52:27">http://www.pronto.com/prodRedirExitInterst.do?exitPoint=nraq&amp;merchantProductId=1894290603&amp;pageLocation=ProductImage&amp;parentId=-290ae334-145861e246f-1d0d&amp;shouldLookupGuidesterCpc=true</link><title>Life After SCI Spinal Cord Injury Volume 2: Transfering and Adapting</title><description>Life After SCI Spinal Cord Injury Volume 2: Transfering and Adapting</description><thumb cache="FW14-topics-docs/e146/7173_02_thumb.jpg">http://cache-images.pronto.com/thumb2.php?src=http%3A%2F%2Fimages.pronto.com%2Fimages%2Fproduction%2Fproducts%2F8d%2F66%2Fimage702aaeac629dee0f3d77cc6919d-1388986727_119x160.jpg&amp;wmax=180&amp;hmax=180&amp;quality=80&amp;bgcol=FFFFFF</thumb></snippet><snippet id="FW14-e146-7173-03"><link cache="FW14-topics-docs/e146/7173_03.html" timestamp="2014-04-21 23:52:56">http://www.pronto.com/prodRedirExitInterst.do?exitPoint=nraq&amp;goldenProductId=11516384267&amp;merchantProductId=1637383077&amp;pageLocation=ProductImage&amp;parentId=-290ae334-145861e246f-1d0d&amp;shouldLookupGuidesterCpc=true</link><title>Spinal Health U-GuLi (60 cap)-100% herbal,good improve on spinal cord and vertebral disorders. (soreness and pain in the shoulder and arms, neck, dizziness, low back pain, soreness and numbness of the legs..)</title><description>The Symptoms that U-GuLi can be used to improve : 1. Symptoms like chest tightness, palpitation, insufficient lung capacity, difficulty breathing, stiffness, soreness and pain of the sho... More »</description><thumb cache="FW14-topics-docs/e146/7173_03_thumb.jpg">http://cache-images.pronto.com/thumb2.php?src=http%3A%2F%2Fimages.pronto.com%2Fimages%2Fproduction%2Fproducts%2Fc2%2F50%2Fimag390877a77d1a63e6dd2d6782d0be-1379394649_94x160.jpg&amp;wmax=180&amp;hmax=180&amp;quality=80&amp;bgcol=FFFFFF</thumb></snippet><snippet id="FW14-e146-7173-04"><link cache="FW14-topics-docs/e146/7173_04.html" timestamp="2014-04-21 23:54:46">http://www.pronto.com/prodRedirExitInterst.do?exitPoint=nraq&amp;goldenProductId=11537732063&amp;merchantProductId=2309174273&amp;pageLocation=ProductImage&amp;parentId=-290ae334-145861e246f-1d0d&amp;shouldLookupGuidesterCpc=true</link><title>Physiological Effects of Spinal Cord Injury on Cardiovascular Disease Risk</title><description>Physiological Effects of Spinal Cord Injury on Cardiovascular Disease Risk presents the most recent scientific findings about the underlying physiological changes consequent to spinal cor... More »</description><thumb cache="FW14-topics-docs/e146/7173_04_thumb.jpg">http://cache-images.pronto.com/thumb2.php?src=http%3A%2F%2Fimages.pronto.com%2Fimages%2Fproduction%2Fproducts%2Fae%2F5d%2Fimag2f6f66e2014187df900489c30ffc-1359095270_130x160.jpg&amp;wmax=180&amp;hmax=180&amp;quality=80&amp;bgcol=FFFFFF</thumb></snippet><snippet id="FW14-e146-7173-05"><link cache="FW14-topics-docs/e146/7173_05.html" timestamp="2014-04-21 23:56:57">http://www.pronto.com/prodRedirExitInterst.do?exitPoint=nraq&amp;merchantProductId=1594625919&amp;pageLocation=ProductImage&amp;parentId=-290ae334-145861e246f-1d0d&amp;shouldLookupGuidesterCpc=true</link><title>Silver Cord Is Severed/10 Years Live Not Dead</title><description>Mortification remains one of the most prominent representatives of the Christian metal scene. The powerful message preached by Mortification makes each of their albums an unforgettable ex... More »</description><thumb cache="FW14-topics-docs/e146/7173_05_thumb.jpg">http://cache-images.pronto.com/thumb2.php?src=http%3A%2F%2Fimages.pronto.com%2Fimages%2Fproduction%2Fproducts%2F1e%2F2c%2Fimagfda9ac22f7fdbada5827c1185555-1395296584_160x143.jpg&amp;wmax=180&amp;hmax=180&amp;quality=80&amp;bgcol=FFFFFF</thumb></snippet><snippet id="FW14-e146-7173-06"><link cache="FW14-topics-docs/e146/7173_06.html" timestamp="2014-04-21 23:59:02">http://www.pronto.com/compare/3-ft-heavy-duty-power-11504786052?pageLocation=ProductImage</link><title>3 Ft Heavy Duty Power Cord</title><description>A large selection of power cords including input power, adapter, and jumper power cords fulfill a variety of power requirements. New locking IEC power cords feature a patented, easy to us... More »</description><thumb cache="FW14-topics-docs/e146/7173_06_thumb.jpg">http://cache-images.pronto.com/thumb2.php?src=http%3A%2F%2Fimages.pronto.com%2Fimages%2Fproduction%2Fproducts%2F8f%2F1b%2Fpricc74f927457979cc4ba758901ce7c-1395465552_160x128.jpg&amp;wmax=180&amp;hmax=180&amp;quality=80&amp;bgcol=FFFFFF</thumb></snippet><snippet id="FW14-e146-7173-07"><link cache="FW14-topics-docs/e146/7173_07.html" timestamp="2014-04-22 00:01:20">http://www.pronto.com/compare/besa-canto-5-pendant-1-11580030758?pageLocation=ProductImage</link><title>Besa Canto 5 Pendant-1-5131OP Canto-5 - Low Voltage One Light Pendant, Bicolor Orange/Pina Glass</title><description>Collection: Canto, Material: Brass/Aluminum, - Desc: the socket holder. Jacket tint coordinates with metal finish. Cords also available in 15 lengths. STANDARD PENDANT (1XC, 1XT) Mini ... More »</description><thumb cache="FW14-topics-docs/e146/7173_07_thumb.jpg">http://cache-images.pronto.com/thumb2.php?src=http%3A%2F%2Fimages.pronto.com%2Fimages%2Fproduction%2Fproducts%2F6a%2F4a%2F1sto792a69dc607ce427ec5002c2fb93-1395397978_96x264.jpg&amp;wmax=180&amp;hmax=180&amp;quality=80&amp;bgcol=FFFFFF</thumb></snippet><snippet id="FW14-e146-7173-08"><link cache="FW14-topics-docs/e146/7173_08.html" timestamp="2014-04-22 00:04:42">http://www.pronto.com/compare/besa-stilo-7-mini-pendant-11580126555?pageLocation=ProductImage</link><title>Besa Stilo 7 Mini-Pendant-1-440419 Stilo-7 - Low Voltage One Light Pendant, Carrera Glass</title><description>Save 10% with LIGHT10 at checkout. Price reflects savings. Ends 04/21/14. - Carrera is a classic yet modern dcor that gives off a soft white light. Clear molten glass is rolled in alabast... More »</description><thumb cache="FW14-topics-docs/e146/7173_08_thumb.jpg">http://cache-images.pronto.com/thumb2.php?src=http%3A%2F%2Fimages.pronto.com%2Fimages%2Fproduction%2Fproducts%2F2f%2Fda%2Fpric08b1909b46695f62825cd5de1029-1397912922_152x464.jpg&amp;wmax=180&amp;hmax=180&amp;quality=80&amp;bgcol=FFFFFF</thumb></snippet><snippet id="FW14-e146-7173-09"><link cache="FW14-topics-docs/e146/7173_09.html" timestamp="2014-04-22 00:07:02">http://www.pronto.com/compare/tripp-lite-p024-003-3-11574256791?pageLocation=ProductImage</link><title>Tripp Lite P024-003 3-Feet 14AWG 15A 120V 5-15R to 5-15P Heavy Duty Power Extension Cord</title><description>Tripp Lite's P024-003 3 ft. Heavy Duty Power Extension Cord allows you to extend the length of your existing power cord an additional 3 ft.. Features a NEMA 5-15R receptacle and a NEMA 5-... More »</description><thumb cache="FW14-topics-docs/e146/7173_09_thumb.jpg">http://cache-images.pronto.com/thumb2.php?src=http%3A%2F%2Fimages.pronto.com%2Fimages%2Fproduction%2Fproducts%2Fe7%2F1d%2Fimagb3699ad63f9dbd0893440b004865-1381142707_160x160.jpg&amp;wmax=180&amp;hmax=180&amp;quality=80&amp;bgcol=FFFFFF</thumb></snippet></snippets></search_results>