<?xml version='1.0' encoding='UTF-8'?>
<search_results><query id="7328">reduce acne redness</query><engine status="OK" timestamp="2014-04-26 04:53:20" name="Disney Family" id="FW14-e086"/><snippets><snippet id="FW14-e086-7328-01"><link cache="FW14-topics-docs/e086/7328_01.html" timestamp="2014-04-26 04:53:22">http://family.go.com/parenting/pkg-teen/article-773418-help-for-your-teen-s-acne-problems-t/</link><title>Help for Your Teen's Acne Problems</title><description>Find Treatments For Your Teen's Acne and Blemish Problems</description></snippet><snippet id="FW14-e086-7328-02"><link cache="FW14-topics-docs/e086/7328_02.html" timestamp="2014-04-26 04:53:55">http://family.go.com/parenting/pkg-teen/article-772576-helping-your-teen-cope-with-acne-t/</link><title>Helping Your Teen Cope with Acne</title><description>How to Provide Your Teen With Resources to Treat Acne</description></snippet><snippet id="FW14-e086-7328-03"><link cache="FW14-topics-docs/e086/7328_03.html" timestamp="2014-04-26 04:54:29">http://family.go.com/food/recipe-639661-red-potato-salad-with-roasted-garlic-t/</link><title>Red Potato Salad with Roasted Garlic</title><description>I've heard tell of those who find the football game secondary to the tailgate party. I'm one of those people. Don't get me wrong; I love a good football game, but the fun had with others on a crisp fall day sharing our ...</description></snippet><snippet id="FW14-e086-7328-04"><link cache="FW14-topics-docs/e086/7328_04.html" timestamp="2014-04-26 04:54:58">http://family.go.com/self/article-814415-skin-science--t/</link><title>Skin Science #sponsorLogoAdd { float: right; }</title><description>Choose An Age-Defying Method That Is Right for You</description></snippet><snippet id="FW14-e086-7328-05"><link cache="FW14-topics-docs/e086/7328_05.html" timestamp="2014-04-26 04:55:20">http://family.go.com/parenting/pkg-teen/article-773712-coping-with-teen-acne-t/</link><title>Coping With Teen Acne</title><description>Find Treatments for Acne to Help Your Teen Cope</description></snippet><snippet id="FW14-e086-7328-06"><link cache="FW14-topics-docs/e086/7328_06.html" timestamp="2014-04-26 04:55:55">http://spoonful.com/recipes/bacon-and-cheese-appetizer-bites</link><title>Red Onion &amp; Goat Cheese Pancake</title><description>The technique for this pancake is similar to that for a Dutch baby or German pancake, but the savory onion and goat cheese combination is a surprise for those who think of pancakes as breakfast food only. Serve with a m...</description></snippet><snippet id="FW14-e086-7328-07"><link cache="FW14-topics-docs/e086/7328_07.html" timestamp="2014-04-26 04:56:17">http://family.go.com/food/recipe-766120-red-beans-and-rice-t/</link><title>Red Beans and Rice</title><description>This thick and hearty stew-like dish is Cajun cooking at its finest. Get the recipe for this Louisiana favorite from Short Order Mom here.</description></snippet><snippet id="FW14-e086-7328-08"><link cache="FW14-topics-docs/e086/7328_08.html" timestamp="2014-04-26 04:56:50">http://family.go.com/crafts/craft-1004188-red-queen-easter-egg-t/</link><title>Red Queen Easter Egg</title><description>Here's a fun way to put the impetuous Red Queen in her place -- holding court in this year's lineup of Easter eggs.</description></snippet><snippet id="FW14-e086-7328-09"><link cache="FW14-topics-docs/e086/7328_09.html" timestamp="2014-04-26 04:57:56">http://family.go.com/food/recipe-1035089-red-queen-cookie-kisses-t/</link><title>Red Queen Cookie Kisses</title><description>Inspired by the Red Queen's rosy heart-shaped lips, these sweet cookie kisses make an endearing offering on Valentine's Day.</description></snippet><snippet id="FW14-e086-7328-10"><link cache="FW14-topics-docs/e086/7328_10.html" timestamp="2014-04-26 04:58:29">http://family.go.com/parenting/pkg-school-age/article-797235-could-your-child-be-sensitive-to-red-food-dye---t/</link><title>Could Your Child Be Sensitive to Red Food Dye?</title><description>How To Determine If Your Child Is Allergic To Artificial Food Additives</description></snippet></snippets></search_results>