<?xml version='1.0' encoding='UTF-8'?>
<search_results><query id="7403">usc trojans</query><engine status="OK" timestamp="2014-04-26 18:45:18" name="TMZ" id="FW14-e041"/><snippets><snippet id="FW14-e041-7403-01"><link cache="FW14-topics-docs/e041/7403_01.html" timestamp="2014-04-26 18:45:19">http://www.tmz.com/2014/04/22/walmart-heiress-elizabeth-paige-laurie-divorce-support-prenup/</link><title>Walmart Heiress Divorce -- CHUMP CHANGE -- I'm So Rich, I'll Pay His Support</title><description>5 days ago - The heiress to the Walmart fortune is so rich she's asking a judge to allow her husband to take her to the cleaners. Paige Laurie Dubbert -- whose mother inherited a multi-BILLION dollar chunk of the…</description><thumb cache="FW14-topics-docs/e041/7403_01_thumb.jpg">http://ll-media.tmz.com/2014/04/21/0421-paige-laurie-getty-01-100x100.jpg</thumb></snippet><snippet id="FW14-e041-7403-02"><link cache="FW14-topics-docs/e041/7403_02.html" timestamp="2014-04-26 18:46:01">http://www.tmz.com/2014/04/16/nfl-prospect-kelcy-quarles-i-did-nothing-wrong/</link><title>NFL Prospect Kelcy Quarles -- Vows to Clear Name ... I Had NOTHING to Do with Nightclub Beating</title><description>11 days ago - NFL Draft prospect Kelcy Quarles says he was NOT at Greenhouse nightclub during an alleged brawl that left one man badly injured last week ... and says he will do everything he can to clear his…</description><thumb cache="FW14-topics-docs/e041/7403_02_thumb.jpg">http://ll-media.tmz.com/2014/04/16/0416-kelcy-chaz-01-100x100.jpg</thumb></snippet><snippet id="FW14-e041-7403-03"><link cache="FW14-topics-docs/e041/7403_03.html" timestamp="2014-04-26 18:46:37">http://www.tmz.com/2014/03/26/tmz-sports-show-kristin-cavallari-michael-vick-geno-smith-vernon-davis-david-blu-terry-bradshaw-rob-bironas-chris-paul-president-obama/</link><title>TMZ Sports Show: Basketball Star -- Super Sperm to the Rescue</title><description>31 days ago - Israel's sperm crisis -- there's a lack of donors over there -- could be handled (Olivia Pope-style) by one brave athlete! Ex-USC hoops star David Blu says he's ready to step up ... or rise to the…</description><thumb cache="FW14-topics-docs/e041/7403_03_thumb.jpg">http://ll-media.tmz.com/2014/03/26/0326-watch-tmz-sports-primary-100x100.jpg</thumb></snippet><snippet id="FW14-e041-7403-04"><link cache="FW14-topics-docs/e041/7403_04.html" timestamp="2014-04-26 18:47:09">http://www.tmz.com/2014/03/26/david-blu-israeli-sperm-crisis-basketball/</link><title>Ex-USC Basketball Star -- I Can Help End Israeli Sperm Crisis</title><description>31 days ago - Israel is a country in crisis -- there's a major sperm donor shortage and it's affecting the birthrate ... but one major Israeli athlete tells TMZ Sports he's willing to rise to the occasion to…</description><thumb cache="FW14-topics-docs/e041/7403_04_thumb.jpg">http://ll-media.tmz.com/2014/03/26/0326-david-bluthenthal-100x100.jpg</thumb></snippet><snippet id="FW14-e041-7403-05"><link cache="FW14-topics-docs/e041/7403_05.html" timestamp="2014-04-26 18:47:40">http://www.tmz.com/2014/03/18/vince-vaughn-lane-kiffin-manhattan-beach-pad/</link><title>Vince Vaughn -- Buys Lane Kiffin's Beach Mansion</title><description>39 days ago - Lane Kiffin's loss is Vince Vaughn's gain ... because the "Wedding Crashers" star has been ID'd as the mystery buyer who paid $6.5 million for the Manhattan Beach pad Lane Kiffin sold when after he…</description><thumb cache="FW14-topics-docs/e041/7403_05_thumb.jpg">http://ll-media.tmz.com/2014/03/18/0318-vince-vauhgn-lane-kiffin-house-100x100.jpg</thumb></snippet><snippet id="FW14-e041-7403-06"><link cache="FW14-topics-docs/e041/7403_06.html" timestamp="2014-04-26 18:48:04">http://www.tmz.com/2014/03/18/terrelle-pryor-quarterback-training-nfl-video/</link><title>Terrelle Pryor -- I'm BUSTING MY ASS for a Starting Job</title><description>40 days ago - Oakland Raiders quarterback Terrelle Pryor tells TMZ Sports ... he's been training like a maniac this off-season -- waking up at 5AM every day in pursuit of a starting QB job in the NFL. Pryor…</description><thumb cache="FW14-topics-docs/e041/7403_06_thumb.jpg">http://ll-media.tmz.com/2014/03/18/031814-terrelle-pryor-100x100.jpg</thumb></snippet><snippet id="FW14-e041-7403-07"><link cache="FW14-topics-docs/e041/7403_07.html" timestamp="2014-04-26 18:48:44">http://www.tmz.com/2014/03/16/mark-sanchez-ny-jets-shoulder-comeback-injury-video/</link><title>Mark Sanchez -- I'm Ready for My Jets Comeback ... If Jets Want Me Back</title><description>41 days ago - NY Jets quarterback Mark Sanchez says he's ready for battle -- telling TMZ Sports his shoulder feels great and he's focused on winning back his starting job ... if management keeps him around.…</description><thumb cache="FW14-topics-docs/e041/7403_07_thumb.jpg">http://ll-media.tmz.com/2014/03/16/031614-mark-sanchez-100x100.jpg</thumb></snippet><snippet id="FW14-e041-7403-08"><link cache="FW14-topics-docs/e041/7403_08.html" timestamp="2014-04-26 18:49:28">http://www.tmz.com/2014/03/11/hollywood-park-racehorses-exhumed-track/</link><title>Hollywood Park -- Legendary Racehorses Exhumed ... From Trackside Graves</title><description>47 days ago - Forget beating a dead horse, they're EXHUMING them at the Hollywood Park race track ... in an effort to relocate the expired animals before the track is torn down. One of the horses being dug up…</description><thumb cache="FW14-topics-docs/e041/7403_08_thumb.jpg">http://ll-media.tmz.com/2014/03/11/0311-usc-hollywood-park-horse-dig-photos-launch-100x100.jpg</thumb></snippet><snippet id="FW14-e041-7403-09"><link cache="FW14-topics-docs/e041/7403_09.html" timestamp="2014-04-26 18:50:00">http://www.tmz.com/2014/03/11/keyshawn-johnson-snoop-son-usc/</link><title>Snoop Dogg's FB Star Son -- USC Should Be #1 Pick ... Says Keyshawn Johnson</title><description>47 days ago - He's reportedly got 17 scholarship offers ... from Notre Dame to Florida State ... but it doesn't matter because Snoop's son was MADE to play football for USC ... so says Keyshawn Johnson. KJ --…</description><thumb cache="FW14-topics-docs/e041/7403_09_thumb.jpg">http://ll-media.tmz.com/2014/03/11/031114-keyshawn-johnson-primary-100x100.jpg</thumb></snippet><snippet id="FW14-e041-7403-10"><link cache="FW14-topics-docs/e041/7403_10.html" timestamp="2014-04-26 18:50:41">http://www.tmz.com/2014/03/05/usc-basketball-andy-enfield-house-florida-mansion-sale-wife/</link><title>USC Basketball Coach -- I'm No Lane Kiffin ... Takes Big Hit on Florida Home</title><description>52 days ago - Not all USC coaches are created equal ... at least when it comes to real estate -- just ask Trojan basketball coach Andy Enfield who just got rocked in Florida the same week Lane Kiffin made out like…</description><thumb cache="FW14-topics-docs/e041/7403_10_thumb.jpg">http://ll-media.tmz.com/2014/03/05/0305-andy-enfield-house-sold-launch-100x100.jpg</thumb></snippet></snippets></search_results>