<?xml version='1.0' encoding='UTF-8'?>
<search_results><query id="7059">doctor Amsterdam</query><engine status="OK" timestamp="2014-04-20 20:57:52" name="CMU ClueWeb" id="FW14-e055"/><snippets><snippet id="FW14-e055-7059-01"><link cache="FW14-topics-docs/e055/7059_01.html" timestamp="2014-04-20 20:58:12">http://www.ucomparehealthcare.com/drs/new_york/AMSTERDAM.html</link><title>Doctors in Amsterdam NY (New York Physicians)</title><description>* Doctors in Amsterdam NY (New York Physicians) (clueweb12-0705wb-71-28697) http://www.ucomparehealthcare.com/drs/new_york/AMSTERDAM.html Doctors in Amsterdam NY (New York Physicians) Doctors Physicians Dentists Podiatrists Insurance Individual Health Group Life Burial Disability Long Term Care Cancer Medicare Part D Senior Care Nursing Homes Hospitals Clinics &amp; Centers Dialysis Fertility Mammography Pharmacies Jobs Search Jobs Post a Job Doctors Found 83 Home &gt; Doctors &gt; New York (NY) &gt; Amsterdam ... [cached version]</description></snippet><snippet id="FW14-e055-7059-02"><link cache="FW14-topics-docs/e055/7059_02.html" timestamp="2014-04-20 20:59:20">http://dr.doctorsrealm.com/Ohio/OH.html</link><title>Ohio Doctors</title><description>* Ohio Doctors (clueweb12-0306wb-63-20108) http://dr.doctorsrealm.com/Ohio/OH.html Ohio Doctors   Menu       ...MarvinSpeciality: Diagnostic Radiology Joshi, VaneetaSpeciality: Internal Medicine Riedel, William MSpeciality: Optometry Ohio Doctors       doctor listings. Please select a city in Ohio to browse the doctors available. Aberdeen Doctors Ada Doctors Addyston Doctors Aint Marys Doctors Akron Doctors Albany Doctors Albuquerque Doctors Alliance Doctors Amelia Doctors Amherst Doctors Amsterdam Doctors Anderson Doctors Andover Doctors Anna Doctors Ansonia Doctors Antwerp Doctors Apple Creek Doctors Applecreek Doctors Arcanum Doctors Archbold Doctors Arkon Doctors... [cached version]</description></snippet><snippet id="FW14-e055-7059-03"><link cache="FW14-topics-docs/e055/7059_03.html" timestamp="2014-04-20 21:01:20">http://dr.doctorsrealm.com/NewYork/NY.html</link><title>New York Doctors</title><description>* New York Doctors (clueweb12-0306wb-59-07625) http://dr.doctorsrealm.com/NewYork/NY.html ...city in New York to browse the doctors available. Accord Doctors Adams Center Doctors Adams Doctors Addison Doctors Afton Doctors Airmont Doctors Akron Doctors Alabny Doctors Albany Doctors Albertson Doctors Albion Doctors Albnay Doctors Alden Doctors Alder Creek Doctors Alexander Doctors Alexandria Bay Doctors Alex Bay Doctors Alfred Doctors Allegany Doctors Altamont Doctors Amagansett Doctors Amenia Doctors Amherst Doctors Amity Harbor Doctors Amityville Doctors Amsterdam Doctors Andover Doctors Angola Doctors Antwerp Doctors Apalachin Doctors Aquebogue Doctors Arcade Doctors Ardsley Doctors... [cached version]</description></snippet><snippet id="FW14-e055-7059-04"><link cache="FW14-topics-docs/e055/7059_04.html" timestamp="2014-04-20 21:02:45">http://doctor.healthcommunities.com/</link><title>Amsterdam NY</title><description>* Amsterdam NY (clueweb12-1018wb-72-00505) http://local.healthcommunities.com/Amsterdam_NY-cAmsterdam+NY.html ...Urological Concerns Women's Health Search All Health Topics A-Z » Healthy Living Guides Find a Doctor Free Newsletters Tools &amp; Apps Amsterdam Topics In Amsterdam NY 101 Popular Topics Male Health Allergy New Topics Alternative Medicine Pain Avian Flu Pediatric...Sexual Health General Health Vision Human Immunodeficiency Virus Women's Health LGBT Health Amsterdam NY Need to find a doctor around Amsterdam? Here you will have access to all listings related to health topics. Find specialty doctors, physicians, surgeons, pediatricians, and dentists. You will also be able to search and find services... [cached version]</description></snippet><snippet id="FW14-e055-7059-05"><link cache="FW14-topics-docs/e055/7059_05.html" timestamp="2014-04-20 21:06:35">http://www.suggestadoctor.com/doctor_152564_lisa_amsterdam.htm</link><title>Lisa AMSTERDAM MD - Missouri - Obstetrics &amp; Gynecology - Recommended Doctor in SuggestADoctor.com</title><description>* Lisa AMSTERDAM MD - Missouri - Obstetrics &amp; Gynecology - Recommended Doctor in SuggestADoctor.com (clueweb12-0609wb-25-28944) http://www.suggestadoctor.com/doctor_152564_lisa_amsterdam.htm Lisa AMSTERDAM MD - Missouri - Obstetrics &amp; Gynecology - Recommended Doctor in SuggestADoctor.com Doctor!                   In Our Site       In Google List Doctors by:   All Names | Top Doctors | Advanced Search Doctor Login ...PulmonologyPsychiatryRadiologySleep SpecialistSurgeryUrogynecologyUrologyOther AMSTERDAM MD   AMSTERDAM MD Recommended Doctor Lisa AMSTERDAM MD Obstetrics &amp; Gynecology - Missouri Doctor Info Doctor's Name   Lisa AMSTERDAM MD [Are you Lisa AMSTERDAM MD? Register now and customize this page... [cached version]</description></snippet><snippet id="FW14-e055-7059-06"><link cache="FW14-topics-docs/e055/7059_06.html" timestamp="2014-04-20 21:07:27">http://torrentz.eu/ba6c9eb613b85d91acc8de4cdc6cc0382cd2eac9</link><title>John Adams - Doctor Atomic - Amsterdam (2007).avi Free Torrent Download</title><description>* John Adams - Doctor Atomic - Amsterdam (2007).avi Free Torrent Download (clueweb12-0701wb-71-16658) http://torrentz.eu/ba6c9eb613b85d91acc8de4cdc6cc0382cd2eac9 John Adams - Doctor Atomic - Amsterdam (2007).avi Free Torrent Download Doctor Atomic - Amsterdam (2007).avi torrent download locationsDirect Download John Adams - Doctor Atomic - Amsterdam (2007).aviSponsored Linkthepiratebay.se John Adams Doctor Atomic Amsterdam 2007 tvrip NL subs... [cached version]</description></snippet><snippet id="FW14-e055-7059-07"><link cache="FW14-topics-docs/e055/7059_07.html" timestamp="2014-04-20 21:10:33">http://www.amsterdam.info/health/</link><title>Amsterdam.info - Amsterdam doctors, psychologist, health care, pharmacies, clinic, drugs</title><description>* Amsterdam.info - Amsterdam doctors, psychologist, health care, pharmacies, clinic, drugs (clueweb12-0013wb-50-00165) http://www.amsterdam.info/health/ Amsterdam.info - Amsterdam doctors, psychologist, health care, pharmacies, clinic, drugs Amsterdam | Search | Site map | Index   Amsterdam Hotels 80% off Up to 80% discount on selected hotels on Amsterdam's premium site. www.hotels.nl Amsterdam canal cruises Most popular tourist attraction. List of boating companies. www.amsterdam.info Site channels: News Community Events Municipality Print and take Basic facts Attractions Museums Accommodation... [cached version]</description></snippet><snippet id="FW14-e055-7059-08"><link cache="FW14-topics-docs/e055/7059_08.html" timestamp="2014-04-20 21:12:43">http://www.amsterdam.info/health/touristdoctor/</link><title>Amsterdam tourist doctor, Amsterdam physician, medical clinic | Amsterdam.info</title><description>* Amsterdam tourist doctor, Amsterdam physician, medical clinic | Amsterdam.info (clueweb12-0403wb-49-22155) http://www.amsterdam.info/health/touristdoctor/ Amsterdam tourist doctor, Amsterdam physician, medical clinic | Amsterdam.info Amsterdam | Search | Site map | Index   Amsterdam Hotels 80% off Up to 80% discount on selected hotels on Amsterdam's premium site. www.hotels.nl Amsterdam canal cruises Most popular tourist attraction. List of boating companies. www.amsterdam.info Site channels: News Community Events Municipality Print and take Basic facts Attractions Museums Accommodation... [cached version]</description></snippet><snippet id="FW14-e055-7059-09"><link>http://annefrank.1.forumer.com/a/the-girl-in-the-console_post415-.html</link><title>The Girl In The Console</title><description>* The Girl In The Console (clueweb12-1902wb-24-21145) http://annefrank.1.forumer.com/a/the-girl-in-the-console_post415-.html ...the console next!Sure enough, he does!CHLOE: I knew it! Sarah was right!THE DOCTOR: (Comically swiping his quiff into a mass of upward spikes, to Chloe's amusement) I don't get it! Sometimes she just doesn't make any sense at all!CHLOE: What did she say?THE DOCTOR: She said that I must go to Amsterdam back in time as the TARDIS wants to give a special girl an 80th birthday... [cached version]</description></snippet><snippet id="FW14-e055-7059-10"><link cache="FW14-topics-docs/e055/7059_10.html" timestamp="2014-04-20 21:19:11">http://1.forumer.com/splash.html?db=annefrank&amp;id=415</link><title>The Girl In The Console</title><description>* The Girl In The Console (clueweb12-1901wb-59-29383) http://annefrank.1.forumer.com/a/the-girl-in-the-console_post415.html ...the console next!Sure enough, he does!CHLOE: I knew it! Sarah was right!THE DOCTOR: (Comically swiping his quiff into a mass of upward spikes, to Chloe's amusement) I don't get it! Sometimes she just doesn't make any sense at all!CHLOE: What did she say?THE DOCTOR: She said that I must go to Amsterdam back in time as the TARDIS wants to give a special girl an 80th birthday... [cached version]</description></snippet></snippets></search_results>