<?xml version='1.0' encoding='UTF-8'?>
<search_results><query id="7430">conflict mali</query><engine status="OK" timestamp="2014-04-25 03:01:29" name="CMU ClueWeb" id="FW14-e055"/><snippets><snippet id="FW14-e055-7430-01"><link cache="FW14-topics-docs/e055/7430_01.html" timestamp="2014-04-25 03:02:05">http://www1.american.edu/ted/ice/tuareg.htm</link><title>TUAREG</title><description>* TUAREG (clueweb12-1208wb-11-26975) http://www1.american.edu/ted/ice/tuareg.htm TUAREG ICE Case Studies Number 151, August 2005 The Tuareg in Mali and Niger: The Role of Desertification in Violent Conflict by Ann Hershkowitz I. Case Background II. Environment Aspect III. Conflict Aspect IV. Env. - Conflict Overlap V. Related Information ICE Home ICE Cases Possible ICE Cases ICE Template The ICE... [cached version]</description></snippet><snippet id="FW14-e055-7430-02"><link>http://allafrica.com/stories/201202281157.html</link><title>allAfrica.com: Mali: The Tuareg - Between Armed Uprising and Drought</title><description>* allAfrica.com: Mali: The Tuareg - Between Armed Uprising and Drought (clueweb12-0400tw-96-02761) http://allafrica.com/stories/201202281157.html allAfrica.com: Mali: The Tuareg - Between Armed Uprising and Drought ...GuineaEritreaEthiopiaGabonGambiaGhanaGuineaGuinea BissauKenyaLesothoLiberiaLibya MadagascarMalawiMaliMauritaniaMauritiusMoroccoMozambiqueNamibiaNigerNigeriaRwandaSenegalSeychellesSierra Leone SomaliaSouth Africa...Africa BeninBurkina FasoCameroonCape VerdeCote d'IvoireGambiaGhanaGuineaGuinea Bissau LiberiaMaliMauritaniaNigerNigeriaSenegalSierra LeoneSĂŁo TomĂŠ and PrĂ­ncipeTogo Topics All Topics AIDSAfrica on the MoveAgribusinessAid and AssistanceArms and ArmiesArtsAsia, Australia, and AfricaAthleticsBankingBook ReviewsBooksBusinessCapital FlowsChildrenClimateCommoditiesCompanyConflictConstructionCorruptionCurrenciesDebtEcotourismEducationEnergyEnvironment Europe and AfricaExternal RelationsFood and... [cached version]</description></snippet><snippet id="FW14-e055-7430-03"><link>http://allafrica.com/stories/201202101380.html</link><title>allAfrica.com: Mali: UN Agency Steps Up Aid Delivery to Refugees Fleeing Conflict</title><description>* allAfrica.com: Mali: UN Agency Steps Up Aid Delivery to Refugees Fleeing Conflict (clueweb12-0007wb-70-00402) http://allafrica.com/stories/201202101380.html allAfrica.com: Mali: UN Agency Steps Up Aid Delivery to Refugees Fleeing Conflict ...Affairs Media NGO Multimedia Video Audio Document Web Site InFocus Pages PhotoEssays Mali: UN Agency Steps Up Aid Delivery to Refugees Fleeing Conflict 10 February 2012 conflict in Mali, where fighting between Government forces and Tuareg rebels has sent thousands of civilians fleeing to... [cached version]</description></snippet><snippet id="FW14-e055-7430-04"><link>http://www.essentialafrica.com/ea-drum-it/drum-crises-and-conflicts</link><title>Essential Africa - Social news</title><description>* Essential Africa - Social news (clueweb12-1306wb-03-06444) http://www.essentialafrica.com/ea-drum-it/drum-crises-and-conflicts ...Ethiopia Gabon Gambia Ghana Guinea Guinea-Bissau Kenya Lesotho Liberia Libyan Arab Jamahiriya Madagascar Malawi Mali Mauritania Mauritius Mayotte Morocco Mozambique Namibia Niger Nigeria RĂŠunion Rwanda SĂŁo TomĂŠ and PrĂ­ncipe Senegal...that residents fear could lead to violence. Source: Reuters drummed by aisha in Drum Crises &amp; Conflicts (Somalia) 1 day 4 hours ago 0 comments drum comment share /3/ +1 Mali rebels capture Timbuktu, key town as new ruler under pressure Tuareg rebels made a dramatic push across northern Mali today and entered the legendary desert town of Timbuktu, locals said, as the disorganised junta... [cached version]</description></snippet><snippet id="FW14-e055-7430-05"><link>http://www.humansecuritygateway.com/search.php?advanced=yes&amp;regions[]=56</link><title>Human Security Gateway - Search Results</title><description>* Human Security Gateway - Search Results (clueweb12-0905wb-66-24603) http://www.humansecuritygateway.com/search.php?advanced=yes&amp;regions[]=56 ...of these All of these Exact phrase None of these           : Advanced Search Topics ALLArmed Conflict (12604)Armies, Paramilitaries, Non-State Armed Groups (10448)Children and Armed Conflict (1698)Climate Change...has the potential to derail the presidential election scheduled for April 2012. The violence in Maliâs northern territory re-surfaced following the proliferation of Libyan weapons and return of large numbers of former pro-Gaddafi combatants fleeing the aftermath of the Libyan conflict. The analysis also looks at possible ways for the African Union and regional and international... [cached version]</description></snippet><snippet id="FW14-e055-7430-06"><link cache="FW14-topics-docs/e055/7430_06.html" timestamp="2014-04-25 03:05:39">http://www.breakingnews.com/topic/mali/</link><title>Latest breaking news on Mali - breakingnews.com</title><description>* Latest breaking news on Mali - breakingnews.com (clueweb12-1907wb-20-11183) http://www.breakingnews.com/topic/mali Latest breaking news on Mali \- breakingnews.com Mali Turn off topic filter Map Related Share/subscribe Related topics: Mali unrest war/conflict Kati, Koulikoro, ML Bamako, Bamako, ML Tombouctou, Tombouctou, ML Tweet Mali unrest Gunfire erupts in Mali capital on 3rd day of clashes between military junta, soldiers... [cached version]</description></snippet><snippet id="FW14-e055-7430-07"><link>http://www.essentialafrica.com/ea-drum-it/drum-crises-and-conflicts?show=9858&amp;comment=9858</link><title>Essential Africa - Social news</title><description>* Essential Africa - Social news (clueweb12-1500tw-60-08260) http://www.essentialafrica.com/ea-drum-it/drum-crises-and-conflicts?show=9858&amp;comment=9858 ...Ethiopia Gabon Gambia Ghana Guinea Guinea-Bissau Kenya Lesotho Liberia Libyan Arab Jamahiriya Madagascar Malawi Mali Mauritania Mauritius Mayotte Morocco Mozambique Namibia Niger Nigeria RĂŠunion Rwanda SĂŁo TomĂŠ and PrĂ­ncipe Senegal...sea space and say all violations... Source: Reuters Africa drummed by meidcsjnxu in Drum Crises &amp; Conflicts (Guinea-Bissau) 11 hours 39 minutes ago 0 comments drum comment share /3/ +1 Mali asks Mauritania help to sort crisis Mali is calling on Mauritania to help resolve the crisis in the north of the country... [cached version]</description></snippet><snippet id="FW14-e055-7430-08"><link>http://allafrica.com/stories/201202101273.html?utm_source=twitterfeed&amp;utm_medium=twitter</link><title>allAfrica.com: Mali: UNHCR Aid to Countries Receiving People Fleeing Clashes in North</title><description>* allAfrica.com: Mali: UNHCR Aid to Countries Receiving People Fleeing Clashes in North (clueweb12-0000tw-00-03776) http://allafrica.com/stories/201202101273.html?utm_source=twitterfeed&amp;utm_medium=twitter allAfrica.com: Mali: UNHCR Aid to Countries Receiving People Fleeing Clashes in North ...GuineaEritreaEthiopiaGabonGambiaGhanaGuineaGuinea BissauKenyaLesothoLiberiaLibya MadagascarMalawiMaliMauritaniaMauritiusMoroccoMozambiqueNamibiaNigerNigeriaRwandaSenegalSeychellesSierra Leone SomaliaSouth Africa...Africa BeninBurkina FasoCameroonCape VerdeCote d'IvoireGambiaGhanaGuineaGuinea Bissau LiberiaMaliMauritaniaNigerNigeriaSenegalSierra LeoneSĂŁo TomĂŠ and PrĂ­ncipeTogo Topics All Topics AIDSAfrica on the MoveAgribusinessAid and AssistanceArms and ArmiesArtsAsia, Australia, and AfricaAthleticsBankingBook ReviewsBooksBusinessCapital FlowsChildrenClimateCommoditiesCompanyConflictConstructionCorruptionCurrenciesDebtEcotourismEducationEnergyEnvironment Europe and AfricaExternal RelationsFood and... [cached version]</description></snippet><snippet id="FW14-e055-7430-09"><link>http://www.essentialafrica.com/ea-drum-it/drum-crises-and-conflicts?show=9126</link><title>Essential Africa - Social news</title><description>* Essential Africa - Social news (clueweb12-0300tw-58-04309) http://www.essentialafrica.com/ea-drum-it/drum-crises-and-conflicts?show=9126 ...Ethiopia Gabon Gambia Ghana Guinea Guinea-Bissau Kenya Lesotho Liberia Libyan Arab Jamahiriya Madagascar Malawi Mali Mauritania Mauritius Mayotte Morocco Mozambique Namibia Niger Nigeria RĂŠunion Rwanda SĂŁo TomĂŠ and PrĂ­ncipe Senegal...Economy Business News EA Business Updates Calendar Communications EA Communications Updates Internet Provider Telecommunications Crises &amp; Conflicts Development Community Development Development News EA Development Updates EA Classifieds Business Services Electronics Equipment Farming... [cached version]</description></snippet><snippet id="FW14-e055-7430-10"><link>http://allafrica.com/stories/201202071495.html</link><title>allAfrica.com: Mali: Violence in North Forces over 20,000 Into Exile</title><description>* allAfrica.com: Mali: Violence in North Forces over 20,000 Into Exile (clueweb12-0000tw-00-03763) http://allafrica.com/stories/201202071495.html allAfrica.com: Mali: Violence in North Forces over 20,000 Into Exile ...GuineaEritreaEthiopiaGabonGambiaGhanaGuineaGuinea BissauKenyaLesothoLiberiaLibya MadagascarMalawiMaliMauritaniaMauritiusMoroccoMozambiqueNamibiaNigerNigeriaRwandaSenegalSeychellesSierra Leone SomaliaSouth Africa...Africa BeninBurkina FasoCameroonCape VerdeCote d'IvoireGambiaGhanaGuineaGuinea Bissau LiberiaMaliMauritaniaNigerNigeriaSenegalSierra LeoneSĂŁo TomĂŠ and PrĂ­ncipeTogo Topics All Topics AIDSAfrica on the MoveAgribusinessAid and AssistanceArms and ArmiesArtsAsia, Australia, and AfricaAthleticsBankingBook ReviewsBooksBusinessCapital FlowsChildrenClimateCommoditiesCompanyConflictConstructionCorruptionCurrenciesDebtEcotourismEducationEnergyEnvironment Europe and AfricaExternal RelationsFood and... [cached version]</description></snippet></snippets></search_results>