<?xml version='1.0' encoding='UTF-8'?>
<search_results><query id="7241">flight simulators</query><engine status="OK" timestamp="2014-04-25 15:30:19" name="National geographic" id="FW14-e181"/><snippets><snippet id="FW14-e181-7241-01"><link cache="FW14-topics-docs/e181/7241_01.html" timestamp="2014-04-25 15:30:21">http://channel.nationalgeographic.com/channel/live-from-space/galleries/preparing-for-liftoff/</link><title>Preparing For Liftoff | National Geographic Channel</title><description>Astronaut candidates are trained in a multitude of subjects, becoming proficient in medical procedures, public speaking, emergency preparedness, survival training, and language classes—for the Expedition 38 crew speaking Russian is essential in communicating with Russian Mission Control Center. In o</description><thumb cache="FW14-topics-docs/e181/7241_01_thumb.jpg">http://members.nationalgeographic.com/exposure/transcode/200/0/?url=http://channel.nationalgeographic.com/exposure/content/photo/photo/2079237_zero-gravity-training_rttrne3wrofabno5r657ctsqt7ncurxrbvj6lwuht2ya6mzmafma_200x200.jpg</thumb></snippet><snippet id="FW14-e181-7241-02"><link cache="FW14-topics-docs/e181/7241_02.html" timestamp="2014-04-25 15:31:36">http://channel.nationalgeographic.com/channel/live-from-space/galleries/meet-the-crew/</link><title>Meet the Crew of Expedition 38 | National Geographic ...</title><description>Meet the 38th crew of astronauts and cosmonauts living and working aboard the International Space Station.</description><thumb cache="FW14-topics-docs/e181/7241_02_thumb.jpg">http://members.nationalgeographic.com/exposure/transcode/200/0/?url=http://channel.nationalgeographic.com/exposure/content/photo/photo/2078392_expedition-crew-38-portrait_gxm5hwoljuohbbjyv3ljywukxhcj7vq7fo25elzxyug5jje2fdsq_200x200.jpg</thumb></snippet><snippet id="FW14-e181-7241-03"><link cache="FW14-topics-docs/e181/7241_03.html" timestamp="2014-04-25 15:32:34">http://ngm-beta.nationalgeographic.com/archive/the-making-of-an-astronaut/</link><title>The Making of an Astronaut | National Geographic Magazine</title><description>The Making of an Astronaut</description><thumb cache="FW14-topics-docs/e181/7241_03_thumb.jpg">http://members.nationalgeographic.com/exposure/transcode/200/0/?url=http://ngm-beta.nationalgeographic.com/exposure/content/photo/photo/11564_realview_2777_53457_6fpnrqpvsi6glubub7mzt6jovxgilbx2563ketuf5k2cf2xb226a_300x300.jpg</thumb></snippet><snippet id="FW14-e181-7241-04"><link cache="FW14-topics-docs/e181/7241_04.html" timestamp="2014-04-25 15:33:07">http://ngm-beta.nationalgeographic.com/archive/the-flight-of-apollo-11-one-giant-leap-for-mankind/</link><title>The Flight of Apollo 11: " One Giant Leap For Mankind " ...</title><description>The Flight of Apollo 11: " One Giant Leap For Mankind "</description><thumb cache="FW14-topics-docs/e181/7241_04_thumb.jpg">http://members.nationalgeographic.com/exposure/transcode/200/0/?url=http://ngm-beta.nationalgeographic.com/exposure/content/photo/photo/22559_realview_4881_53483_fbgjup7j7tloj6djzoxtw74gyhgilbx2563ketuf5k2cf2xb226a_300x300.jpg</thumb></snippet><snippet id="FW14-e181-7241-05"><link cache="FW14-topics-docs/e181/7241_05.html" timestamp="2014-04-25 15:33:46">http://ngm-beta.nationalgeographic.com/archive/the-air-safety-challenge/</link><title>The Air-Safety Challenge | National Geographic Magazine</title><description>The Air-Safety Challenge</description><thumb cache="FW14-topics-docs/e181/7241_05_thumb.jpg">http://members.nationalgeographic.com/exposure/transcode/200/0/?url=http://ngm-beta.nationalgeographic.com/exposure/content/photo/photo/14542_realview_2546_54266_ha3vlafauwrtyd2jhsbiokeoedgilbx2563ketuf5k2cf2xb226a_300x300.jpg</thumb></snippet><snippet id="FW14-e181-7241-06"><link cache="FW14-topics-docs/e181/7241_06.html" timestamp="2014-04-25 15:34:37">http://www.nationalgeographic.com/explorers/bios/barrington-irving/</link><title>Barrington Irving, Pilot and Educator Information, Facts, News ...</title><description>Get information, facts, and more about Barrington Irving, Pilot and Educator from National Geographic.</description><thumb cache="FW14-topics-docs/e181/7241_06_thumb.jpg">http://members.nationalgeographic.com/exposure/transcode/200/0/?url=http://www.nationalgeographic.com/u/TvyamNb-BivtNwpvn7Sct0VFDulyAfA9wBcU0gVHVnqC5ghrMYjoba6DkBkzl8-7iLbQvFqj61iiDe7RN9I/</thumb></snippet><snippet id="FW14-e181-7241-07"><link cache="FW14-topics-docs/e181/7241_07.html" timestamp="2014-04-25 15:35:13">http://ngm-beta.nationalgeographic.com/archive/columbia-s-landing-closes-a-circle/</link><title>Columbia' s Landing Closes a Circle | National Geographic ...</title><description>Columbia' s Landing Closes a Circle</description><thumb cache="FW14-topics-docs/e181/7241_07_thumb.jpg">http://members.nationalgeographic.com/exposure/transcode/200/0/?url=http://ngm-beta.nationalgeographic.com/exposure/content/photo/photo/14004_realview_2977_53894_buphyt3gnahufvrn4gsbavxu6hgilbx2563ketuf5k2cf2xb226a_300x300.jpg</thumb></snippet><snippet id="FW14-e181-7241-08"><link cache="FW14-topics-docs/e181/7241_08.html" timestamp="2014-04-25 15:36:00">http://phenomena.nationalgeographic.com/2008/10/08/microraptor-the-dinosaur-that-flew-like-a-biplane/</link><title>Microraptor – the dinosaur that flew like a biplane ...</title><description>Many of us believe dinosaurs to be extinct but in truth, they surround us every day. All the world's birds, from the pigeons of our cities to the gulls of our seasides, are descended from dinosaurs...</description><thumb cache="FW14-topics-docs/e181/7241_08_thumb.jpg">http://members.nationalgeographic.com/exposure/transcode/200/0/?url=http://phenomena.nationalgeographic.com/files/2012/12/amnh30.jpg</thumb></snippet></snippets></search_results>