<?xml version='1.0' encoding='UTF-8'?>
<search_results><query id="7439">make crown</query><engine status="OK" timestamp="2014-05-23 01:19:03" name="Comedy Central" id="FW14-e020"/><snippets><snippet id="FW14-e020-7439-01"><link cache="FW14-topics-docs/e020/7439_01.html" timestamp="2014-05-23 01:19:13">http://thecolbertreport.cc.com/videos/kza2d8/the-word---tit-for-tat</link><title>The Word - Tit for Tat</title><description>An outraged Stephen speaks out against beauty queen Tara Conner for publicly exhibiting her sexuality, and proposes a change in the pageant scoring system.</description><thumb cache="FW14-topics-docs/e020/7439_01_thumb.jpg">http://comedycentral.mtvnimages.com/images/shows/colbert_report/video_archive/season_2/cr_02160_03_wrd_v6.jpg</thumb></snippet><snippet id="FW14-e020-7439-02"><link cache="FW14-topics-docs/e020/7439_02.html" timestamp="2014-05-23 01:19:15">http://thedailyshow.cc.com/videos/oa0c4m/celebrity-interviews</link><title>Celebrity Interviews</title><description>Jon shares footage of past interviews with the fascinating people publicity agents make available to him.</description><thumb cache="FW14-topics-docs/e020/7439_02_thumb.jpg">http://comedycentral.mtvnimages.com/images/shows/tds/videos/season_05/episode_007/ds_05007_08_msc_v6.jpg</thumb></snippet><snippet id="FW14-e020-7439-03"><link cache="FW14-topics-docs/e020/7439_03.html" timestamp="2014-05-23 01:19:17">http://www.cc.com/video-clips/k8tni0/stand-up-pete-holmes--miracle-otter</link><title>Pete Holmes - Miracle Otter</title><description>The animal that nobody thinks about makes Pete Holmes think.</description><thumb cache="FW14-topics-docs/e020/7439_03_thumb.jpg">http://comedycentral.mtvnimages.com/images/shows/specials/pete_holmes/nicetrythedevil/ccsu_phn_01_0101_16_1920x1080.jpg</thumb></snippet><snippet id="FW14-e020-7439-04"><link cache="FW14-topics-docs/e020/7439_04.html" timestamp="2014-05-23 01:19:25">http://thedailyshow.cc.com/videos/cn9hwj/back-in-brown-with-aasif-mandvi</link><title>Back in Brown with Aasif Mandvi</title><description>An Indian-American wins the Miss America crown, and Aasif Mandvi explains what this means for the rest of the country.</description><thumb cache="FW14-topics-docs/e020/7439_04_thumb.jpg">http://comedycentral.mtvnimages.com/images/shows/tds/videos/season_18/18155/ds_18155_03.jpg</thumb></snippet><snippet id="FW14-e020-7439-05"><link cache="FW14-topics-docs/e020/7439_05.html" timestamp="2014-05-23 01:19:27">http://thecolbertreport.cc.com/videos/dgnc7d/douchebag-showdown</link><title>Douchebag Showdown</title><description>Prince Creme Brawlee of Monaco makes the mistake of getting in the face of all-American super-douche Adam Hock and pays the price.</description><thumb cache="FW14-topics-docs/e020/7439_05_thumb.jpg">http://comedycentral.mtvnimages.com/images/shows/colbert_report/videos/season8/08059/cr_08059_02_16x9.jpg</thumb></snippet><snippet id="FW14-e020-7439-06"><link cache="FW14-topics-docs/e020/7439_06.html" timestamp="2014-05-23 01:19:30">http://www.cc.com/video-clips/al86i6/key-and-peele-obama-s-anger-translator---the-last-four-years</link><title>Obama's Anger Translator - The Last Four Years</title><description>President Obama's anger translator Luther reminds Americans of one of the president's biggest accomplishments.</description><thumb cache="FW14-topics-docs/e020/7439_06_thumb.jpg">http://comedycentral.mtvnimages.com/images/shows/key_and_peele/video/season_1/keyandpeele_103_obama_tunein_640x360.jpg</thumb></snippet><snippet id="FW14-e020-7439-07"><link cache="FW14-topics-docs/e020/7439_07.html" timestamp="2014-05-23 01:19:35">http://thedailyshow.cc.com/videos/q2fpnr/back-in-black---product-recalls</link><title>Back in Black - Product Recalls</title><description>If Lewis Black didn't know any better, he'd think companies selling broken cars and poisoned medicines are just in it for the money.</description><thumb cache="FW14-topics-docs/e020/7439_07_thumb.jpg">http://comedycentral.mtvnimages.com/images/shows/tds/videos/season_15/15089/ds_15089_03_16x9.jpg</thumb></snippet><snippet id="FW14-e020-7439-08"><link>http://www.cc.com/cc-studios/behind-amy-schumer/mx3fwz/behind-amy-schumer---amy-on-stage---uncensored</link><title>Behind Amy Schumer - Amy on Stage - Uncensored</title><description>Amy notes the differences between male and female comedians and riffs with everyone from her cab driver to audience members.</description><thumb cache="FW14-topics-docs/e020/7439_08_thumb.png">http://comedycentral.mtvnimages.com/images/ccstudios/video/behind_amy_schumer_105.png</thumb></snippet><snippet id="FW14-e020-7439-09"><link cache="FW14-topics-docs/e020/7439_09.html" timestamp="2014-05-23 01:19:48">http://thedailyshow.cc.com/videos/kgusqz/esperanza-spalding----black-gold-</link><title>Esperanza Spalding - "Black Gold"</title><description>Esperanza Spalding and the Radio Music Society perform "Black Gold," off of her album, "Radio Music Society."</description><thumb cache="FW14-topics-docs/e020/7439_09_thumb.jpg">http://comedycentral.mtvnimages.com/images/shows/tds/videos/season_17/17087/ds_17087_04_16x9.jpg</thumb></snippet><snippet id="FW14-e020-7439-10"><link cache="FW14-topics-docs/e020/7439_10.html" timestamp="2014-05-23 01:19:50">http://thecolbertreport.cc.com/videos/45yrtw/peggielene-bartels</link><title>Peggielene Bartels</title><description>Peggielene Bartels describes the Ghanaian libation ritual and discusses her achievements as the king of Otuam.</description><thumb cache="FW14-topics-docs/e020/7439_10_thumb.jpg">http://comedycentral.mtvnimages.com/images/shows/colbert_report/videos/season8/08062/cr_08062_04_16x9.jpg</thumb></snippet></snippets></search_results>